<?xml version="1.0" encoding="utf-8"?>
<dados xmlns:xsi="http://www.w3.org/2001/XMLSchema-instance">
  <rota name="MG" cidade="CONCEIÇÃO DO MATO DENTRO">
    <data>21/01/2026</data>
    <nomeCurto>QUARTEL</nomeCurto>
    <nomeCompleto> </nomeCompleto>
    <endereco> </endereco>
    <horario>Horário de 08:00 às 13:00</horario>
    <site> </site>
    <mapa> </mapa>
  </rota>
  <rota name="MG" cidade="MADRE DE DEUS DE MINAS">
    <data>26/01/2026</data>
    <nomeCurto>PRESÍDIO</nomeCurto>
    <nomeCompleto> </nomeCompleto>
    <endereco> </endereco>
    <horario>Horário de 08:00 às 14:00</horario>
    <site> </site>
    <mapa> </mapa>
  </rota>
  <rota name="MG" cidade="TEIXEIRAS">
    <data>29/01/2026</data>
    <nomeCurto>PÁTIO</nomeCurto>
    <nomeCompleto> </nomeCompleto>
    <endereco> </endereco>
    <horario>Horário de 10:00 às 16:00</horario>
    <site> </site>
    <mapa> </mapa>
  </rota>
  <rota name="MG" cidade="JABOTICATUBAS">
    <data>30/01/2026</data>
    <nomeCurto>TESTE</nomeCurto>
    <nomeCompleto> </nomeCompleto>
    <endereco> </endereco>
    <horario>Horário de 14:00 às 18:00</horario>
    <site> </site>
    <mapa> </mapa>
  </rota>
  <rota name="MG" cidade="TEIXEIRAS">
    <data>30/01/2026</data>
    <nomeCurto>ESCOLA</nomeCurto>
    <nomeCompleto> </nomeCompleto>
    <endereco> </endereco>
    <horario>Horário de 08:00 às 12:00</horario>
    <site> </site>
    <mapa> </mapa>
  </rota>
  <rota name="MG" cidade="ABADIA DOS DOURADOS">
    <data>29/01/2026</data>
    <nomeCurto>TESTE</nomeCurto>
    <nomeCompleto> </nomeCompleto>
    <endereco> </endereco>
    <horario>Horário de 15:00 às 20:00</horario>
    <site> </site>
    <mapa> </mapa>
  </rota>
</dados>